{"variants":[{"paths":["\/documentation\/stripepaymentsui\/stpcardformview\/representable\/searchable(text:editabletokens:ispresented:placement:prompt:token:)-5hix6"],"traits":[{"interfaceLanguage":"swift"}]}],"identifier":{"url":"doc:\/\/com.stripe.stripe-payments-ui\/documentation\/StripePaymentsUI\/STPCardFormView\/Representable\/searchable(text:editableTokens:isPresented:placement:prompt:token:)-5hix6","interfaceLanguage":"swift"},"sections":[],"kind":"symbol","abstract":[{"type":"text","text":"Inherited from "},{"type":"codeVoice","code":"View.searchable(text:editableTokens:isPresented:placement:prompt:token:)"},{"type":"text","text":"."}],"primaryContentSections":[{"kind":"declarations","declarations":[{"platforms":["iOS"],"languages":["swift"],"tokens":[{"kind":"attribute","text":"nonisolated"},{"kind":"text","text":" "},{"kind":"keyword","text":"func"},{"kind":"text","text":" "},{"kind":"identifier","text":"searchable"},{"kind":"text","text":"<"},{"kind":"genericParameter","text":"C"},{"kind":"text","text":">("},{"kind":"externalParam","text":"text"},{"kind":"text","text":": "},{"kind":"typeIdentifier","text":"Binding","preciseIdentifier":"s:7SwiftUI7BindingV"},{"kind":"text","text":"<"},{"kind":"typeIdentifier","text":"String","preciseIdentifier":"s:SS"},{"kind":"text","text":">, "},{"kind":"externalParam","text":"editableTokens"},{"kind":"text","text":": "},{"kind":"typeIdentifier","text":"Binding","preciseIdentifier":"s:7SwiftUI7BindingV"},{"kind":"text","text":"<"},{"kind":"typeIdentifier","text":"C"},{"kind":"text","text":">, "},{"kind":"externalParam","text":"isPresented"},{"kind":"text","text":": "},{"kind":"typeIdentifier","text":"Binding","preciseIdentifier":"s:7SwiftUI7BindingV"},{"kind":"text","text":"<"},{"kind":"typeIdentifier","text":"Bool","preciseIdentifier":"s:Sb"},{"kind":"text","text":">, "},{"kind":"externalParam","text":"placement"},{"kind":"text","text":": "},{"kind":"typeIdentifier","text":"SearchFieldPlacement","preciseIdentifier":"s:7SwiftUI20SearchFieldPlacementV"},{"kind":"text","text":" = .automatic, "},{"kind":"externalParam","text":"prompt"},{"kind":"text","text":": "},{"kind":"typeIdentifier","text":"Text","preciseIdentifier":"s:7SwiftUI4TextV"},{"kind":"text","text":"? = nil, "},{"kind":"attribute","text":"@"},{"kind":"attribute","text":"ViewBuilder","preciseIdentifier":"s:7SwiftUI11ViewBuilderV"},{"kind":"text","text":" "},{"kind":"externalParam","text":"token"},{"kind":"text","text":": "},{"kind":"attribute","text":"@escaping "},{"kind":"text","text":"("},{"kind":"typeIdentifier","text":"Binding","preciseIdentifier":"s:7SwiftUI7BindingV"},{"kind":"text","text":"<"},{"kind":"typeIdentifier","text":"C"},{"kind":"text","text":"."},{"kind":"typeIdentifier","text":"Element","preciseIdentifier":"s:ST7ElementQa"},{"kind":"text","text":">) -> "},{"kind":"keyword","text":"some"},{"kind":"text","text":" "},{"kind":"typeIdentifier","text":"View","preciseIdentifier":"s:7SwiftUI4ViewP"},{"kind":"text","text":") -> "},{"kind":"keyword","text":"some"},{"kind":"text","text":" "},{"kind":"typeIdentifier","text":"View","preciseIdentifier":"s:7SwiftUI4ViewP"},{"kind":"text","text":" "},{"kind":"keyword","text":"where"},{"kind":"text","text":" "},{"kind":"typeIdentifier","text":"C"},{"kind":"text","text":" : "},{"kind":"typeIdentifier","text":"RandomAccessCollection","preciseIdentifier":"s:Sk"},{"kind":"text","text":", "},{"kind":"typeIdentifier","text":"C"},{"kind":"text","text":" : "},{"kind":"typeIdentifier","text":"RangeReplaceableCollection","preciseIdentifier":"s:Sm"},{"kind":"text","text":", "},{"kind":"typeIdentifier","text":"C"},{"kind":"text","text":"."},{"kind":"typeIdentifier","text":"Element","preciseIdentifier":"s:ST7ElementQa"},{"kind":"text","text":" : "},{"kind":"typeIdentifier","text":"Identifiable","preciseIdentifier":"s:s12IdentifiableP"},{"kind":"text","text":"\n"}]}]}],"schemaVersion":{"patch":0,"major":0,"minor":3},"metadata":{"roleHeading":"Instance Method","fragments":[{"text":"func","kind":"keyword"},{"text":" ","kind":"text"},{"text":"searchable","kind":"identifier"},{"text":"<","kind":"text"},{"text":"C","kind":"genericParameter"},{"text":">(","kind":"text"},{"text":"text","kind":"externalParam"},{"text":": ","kind":"text"},{"text":"Binding","kind":"typeIdentifier","preciseIdentifier":"s:7SwiftUI7BindingV"},{"text":"<","kind":"text"},{"text":"String","kind":"typeIdentifier","preciseIdentifier":"s:SS"},{"text":">, ","kind":"text"},{"text":"editableTokens","kind":"externalParam"},{"text":": ","kind":"text"},{"text":"Binding","kind":"typeIdentifier","preciseIdentifier":"s:7SwiftUI7BindingV"},{"text":"<","kind":"text"},{"text":"C","kind":"typeIdentifier"},{"text":">, ","kind":"text"},{"text":"isPresented","kind":"externalParam"},{"text":": ","kind":"text"},{"text":"Binding","kind":"typeIdentifier","preciseIdentifier":"s:7SwiftUI7BindingV"},{"text":"<","kind":"text"},{"text":"Bool","kind":"typeIdentifier","preciseIdentifier":"s:Sb"},{"text":">, ","kind":"text"},{"text":"placement","kind":"externalParam"},{"text":": ","kind":"text"},{"text":"SearchFieldPlacement","kind":"typeIdentifier","preciseIdentifier":"s:7SwiftUI20SearchFieldPlacementV"},{"text":", ","kind":"text"},{"text":"prompt","kind":"externalParam"},{"text":": ","kind":"text"},{"text":"Text","kind":"typeIdentifier","preciseIdentifier":"s:7SwiftUI4TextV"},{"text":"?, ","kind":"text"},{"text":"token","kind":"externalParam"},{"text":": (","kind":"text"},{"text":"Binding","kind":"typeIdentifier","preciseIdentifier":"s:7SwiftUI7BindingV"},{"text":"<","kind":"text"},{"text":"C","kind":"typeIdentifier"},{"text":".","kind":"text"},{"text":"Element","kind":"typeIdentifier","preciseIdentifier":"s:ST7ElementQa"},{"text":">) -> ","kind":"text"},{"text":"some","kind":"keyword"},{"text":" ","kind":"text"},{"text":"View","kind":"typeIdentifier","preciseIdentifier":"s:7SwiftUI4ViewP"},{"text":") -> ","kind":"text"},{"text":"some","kind":"keyword"},{"text":" ","kind":"text"},{"text":"View","kind":"typeIdentifier","preciseIdentifier":"s:7SwiftUI4ViewP"}],"symbolKind":"method","role":"symbol","title":"searchable(text:editableTokens:isPresented:placement:prompt:token:)","platforms":[{"introducedAt":"17.0","name":"iOS","deprecated":false,"beta":false,"unavailable":false},{"introducedAt":"17.0","name":"iPadOS","deprecated":false,"beta":false,"unavailable":false},{"introducedAt":"17.0","name":"Mac Catalyst","deprecated":false,"beta":false,"unavailable":false},{"introducedAt":"14.0","name":"macOS","deprecated":false,"beta":false,"unavailable":false}],"extendedModule":"SwiftUICore","externalID":"s:7SwiftUI4ViewPAAE10searchable4text14editableTokens11isPresented9placement6prompt5tokenQrAA7BindingVySSG_ALyqd__GALySbGAA20SearchFieldPlacementVAA4TextVSgqd_0_ALy7ElementSTQyd__GctSkRd__SmRd__AaBRd_0_s12IdentifiableAVRQr0_lF::SYNTHESIZED::s:16StripePaymentsUI15STPCardFormViewC13RepresentableV","modules":[{"name":"StripePaymentsUI","relatedModules":["SwiftUICore"]}]},"hierarchy":{"paths":[["doc:\/\/com.stripe.stripe-payments-ui\/documentation\/StripePaymentsUI","doc:\/\/com.stripe.stripe-payments-ui\/documentation\/StripePaymentsUI\/STPCardFormView","doc:\/\/com.stripe.stripe-payments-ui\/documentation\/StripePaymentsUI\/STPCardFormView\/Representable"]]},"references":{"doc://com.stripe.stripe-payments-ui/documentation/StripePaymentsUI/STPCardFormView/Representable":{"navigatorTitle":[{"text":"Representable","kind":"identifier"}],"title":"STPCardFormView.Representable","type":"topic","identifier":"doc:\/\/com.stripe.stripe-payments-ui\/documentation\/StripePaymentsUI\/STPCardFormView\/Representable","abstract":[{"type":"text","text":"A SwiftUI representation of STPCardFormView"}],"role":"symbol","url":"\/documentation\/stripepaymentsui\/stpcardformview\/representable","kind":"symbol","fragments":[{"text":"struct","kind":"keyword"},{"text":" ","kind":"text"},{"text":"Representable","kind":"identifier"}]},"doc://com.stripe.stripe-payments-ui/documentation/StripePaymentsUI/STPCardFormView/Representable/searchable(text:editableTokens:isPresented:placement:prompt:token:)-5hix6":{"title":"searchable(text:editableTokens:isPresented:placement:prompt:token:)","type":"topic","abstract":[],"url":"\/documentation\/stripepaymentsui\/stpcardformview\/representable\/searchable(text:editabletokens:ispresented:placement:prompt:token:)-5hix6","identifier":"doc:\/\/com.stripe.stripe-payments-ui\/documentation\/StripePaymentsUI\/STPCardFormView\/Representable\/searchable(text:editableTokens:isPresented:placement:prompt:token:)-5hix6","kind":"symbol","fragments":[{"kind":"keyword","text":"func"},{"kind":"text","text":" "},{"kind":"identifier","text":"searchable"},{"kind":"text","text":"<"},{"kind":"genericParameter","text":"C"},{"kind":"text","text":">("},{"kind":"externalParam","text":"text"},{"kind":"text","text":": "},{"preciseIdentifier":"s:7SwiftUI7BindingV","kind":"typeIdentifier","text":"Binding"},{"kind":"text","text":"<"},{"preciseIdentifier":"s:SS","kind":"typeIdentifier","text":"String"},{"kind":"text","text":">, "},{"kind":"externalParam","text":"editableTokens"},{"kind":"text","text":": "},{"preciseIdentifier":"s:7SwiftUI7BindingV","kind":"typeIdentifier","text":"Binding"},{"kind":"text","text":"<"},{"kind":"typeIdentifier","text":"C"},{"kind":"text","text":">, "},{"kind":"externalParam","text":"isPresented"},{"kind":"text","text":": "},{"preciseIdentifier":"s:7SwiftUI7BindingV","kind":"typeIdentifier","text":"Binding"},{"kind":"text","text":"<"},{"preciseIdentifier":"s:Sb","kind":"typeIdentifier","text":"Bool"},{"kind":"text","text":">, "},{"kind":"externalParam","text":"placement"},{"kind":"text","text":": "},{"preciseIdentifier":"s:7SwiftUI20SearchFieldPlacementV","kind":"typeIdentifier","text":"SearchFieldPlacement"},{"kind":"text","text":", "},{"kind":"externalParam","text":"prompt"},{"kind":"text","text":": "},{"preciseIdentifier":"s:7SwiftUI4TextV","kind":"typeIdentifier","text":"Text"},{"kind":"text","text":"?, "},{"kind":"externalParam","text":"token"},{"kind":"text","text":": ("},{"preciseIdentifier":"s:7SwiftUI7BindingV","kind":"typeIdentifier","text":"Binding"},{"kind":"text","text":"<"},{"kind":"typeIdentifier","text":"C"},{"kind":"text","text":"."},{"preciseIdentifier":"s:ST7ElementQa","kind":"typeIdentifier","text":"Element"},{"kind":"text","text":">) -> "},{"kind":"keyword","text":"some"},{"kind":"text","text":" "},{"preciseIdentifier":"s:7SwiftUI4ViewP","kind":"typeIdentifier","text":"View"},{"kind":"text","text":") -> "},{"kind":"keyword","text":"some"},{"kind":"text","text":" "},{"preciseIdentifier":"s:7SwiftUI4ViewP","kind":"typeIdentifier","text":"View"}],"role":"symbol"},"doc://com.stripe.stripe-payments-ui/documentation/StripePaymentsUI":{"type":"topic","abstract":[{"text":"The StripePaymentsUI module contains UI elements and API bindings for building a custom payment flow using Stripe.","type":"text"}],"role":"collection","title":"StripePaymentsUI","identifier":"doc:\/\/com.stripe.stripe-payments-ui\/documentation\/StripePaymentsUI","kind":"symbol","url":"\/documentation\/stripepaymentsui"},"doc://com.stripe.stripe-payments-ui/documentation/StripePaymentsUI/STPCardFormView":{"navigatorTitle":[{"kind":"identifier","text":"STPCardFormView"}],"kind":"symbol","url":"\/documentation\/stripepaymentsui\/stpcardformview","type":"topic","title":"STPCardFormView","fragments":[{"kind":"keyword","text":"class"},{"kind":"text","text":" "},{"kind":"identifier","text":"STPCardFormView"}],"identifier":"doc:\/\/com.stripe.stripe-payments-ui\/documentation\/StripePaymentsUI\/STPCardFormView","abstract":[{"code":"STPCardFormView","type":"codeVoice"},{"type":"text","text":" provides a multiline interface for users to input their"},{"type":"text","text":" "},{"type":"text","text":"credit card details as well as billing postal code and provides an interface to access"},{"type":"text","text":" "},{"type":"text","text":"the created "},{"code":"STPPaymentMethodParams","type":"codeVoice"},{"type":"text","text":"."},{"type":"text","text":" "},{"code":"STPCardFormView","type":"codeVoice"},{"type":"text","text":" includes both the input fields as well as an error label that"},{"type":"text","text":" "},{"type":"text","text":"is displayed when invalid input is detected."}],"role":"symbol"}},"variantOverrides":[{"patch":[{"path":"\/references\/doc:~1~1com.stripe.stripe-payments-ui~1documentation~1StripePaymentsUI~1STPCardFormView\/title","value":"STPCardFormView","op":"replace"},{"path":"\/references\/doc:~1~1com.stripe.stripe-payments-ui~1documentation~1StripePaymentsUI~1STPCardFormView\/fragments","value":[{"text":"STPCardFormView","kind":"identifier"}],"op":"replace"},{"path":"\/references\/doc:~1~1com.stripe.stripe-payments-ui~1documentation~1StripePaymentsUI~1STPCardFormView\/navigatorTitle","value":[{"text":"STPCardFormView","kind":"identifier"}],"op":"replace"}],"traits":[{"interfaceLanguage":"occ"}]}]}